dooti/__init__.py
dooti/cli.py
dooti/dooti.py
dooti-0.2.1.dist-info/entry_points.txt
dooti-0.2.1.dist-info/LICENSE
dooti-0.2.1.dist-info/WHEEL
dooti-0.2.1.dist-info/METADATA
dooti-0.2.1.dist-info/RECORD
