Metadata-Version: 2.1
Name: dooti
Version: 0.2.1
Summary: Manage default file and URI scheme handlers on macOS 12.0+
Home-page: https://github.com/lkubb/dooti
Author: jeanluc
Requires-Python: >=3.10,<4.0
Classifier: Intended Audience :: End Users/Desktop
Classifier: Operating System :: MacOS
Classifier: Programming Language :: Python :: 3
Classifier: Programming Language :: Python :: 3.10
Classifier: Programming Language :: Python :: 3.11
Classifier: Topic :: System :: Systems Administration
Classifier: Topic :: Utilities
Requires-Dist: PyYAML (>=6.0,<7.0)
Requires-Dist: pyobjc-core (>=7.2,<8.0)
Requires-Dist: pyobjc-framework-UniformTypeIdentifiers (>=7.2,<8.0)
Requires-Dist: xdg (>=5.1.1,<6.0.0)
Project-URL: Repository, https://github.com/lkubb/dooti
